CyberGearDriver/__init__.py
CyberGearDriver/can.py
CyberGearDriver/constants.py
CyberGearDriver/event_emitter.py
CyberGearDriver/motor_controller.py
CyberGearDriver/parameters.py
CyberGearDriver/state.py
CyberGearDriver/utils.py
cybergeardriver-0.2.0.dist-info/METADATA
cybergeardriver-0.2.0.dist-info/WHEEL
cybergeardriver-0.2.0.dist-info/licenses/LICENSE
cybergeardriver-0.2.0.dist-info/RECORD
