Metadata-Version: 2.4
Name: CyberGearDriver
Version: 0.2.0
Summary: A driver for the CyberGear micromotor
Project-URL: Homepage, https://github.com/jgillick/python-cybergear
Project-URL: Issues, https://github.com/jgillick/python-cybergear/issues
Author: Jeremy Gillick
License-Expression: MIT
License-File: LICENSE
Classifier: Operating System :: OS Independent
Classifier: Programming Language :: Python :: 3
Requires-Python: >=3.8
